{
    "student_id": "2023130219",
    "name": "궁기",
    "image": "images/궁기.jpg",
    "image_prompt": "궁기(窮奇)**는 특이한 생물로, 그 모습은 호랑이와 유사하며 날개가 있습니다. 이 생물은 사람을 잡아먹을 때 머리부터 먹기 시작합니다. 먹힌 사람의 머리카락은 헝클어져 있다고 합니다. 상상 속 궁기에 대한 이미지를 생성해 주세요.",
    "animals": [
        "범"
    ],
    "original": "窮奇狀如虎，有翼，食人從首始，所食被髮，在蜪犬北.",
    "translated": "궁기(窮奇)는 생김새가 범(虎)과 비슷하고, 날개가 있고, 사람을 먹을 때 머리부터 먹기 시작하는데, 所食被髮，도견(蜪犬)의 북쪽에 있다.",
    "source": "산해경",
    "comment": "궁기는 산해경에서 총 두 번 언급된다. 서산경에서는 개 같은 소리로 짖는 식인 소로 묘사되는데, 해내북경에서는 날개가 달려 날아다니는 식인 호랑이로 묘사된다."
}